{"title": "Beatification Von Galen", "author": "Benedict XVI", "type_of_text": "Apost_letters", "pub_date": "09/10/2005", "text": "APOSTOLIC LETTERBY WHICH THE SUPREME PONTIFF BENEDICT XVI HAS RAISED TO THE GLORY OF THE ALTARSTHE SERVANT OF GOD CLEMENS AUGUST GRAF VON GALEN Accepting the wish of our Brother , Bishop Reinhard Lettmann of M\u00fcnster , of many_other Brothers in the Episcopate and of numerous members of the faithful , after hearing the opinion of the Congregation for the Causes of Saints , we grant , with_our Apostolic Authority , that the Venerable Servant of God Clemens August Count von Galen , henceforth be called Blessed , and that_his Memorial be celebrated , in the places foreseen and in accordance_with_the rules established by law , every year on March , the day of his_death . In the name of the Father , and of the Son and of the Holy Spirit . Given -atti_degli_apostoli- St Peter s in Rome , October in the year of the Lord , the first of Our Pontificate BENEDICT XVI Copyright Libreria Editrice Vaticana", "author_country": "Germania", "author_birth_name": "Joseph Aloisius Ratzinger", "author_dob": "16/04/1927", "author_start": "19/04/2005", "author_end": "28/02/2013", "pontificate_years": 7}